pythonbasictools/__init__.py
pythonbasictools/cmds.py
pythonbasictools/collections_tools.py
pythonbasictools/decorators.py
pythonbasictools/device.py
pythonbasictools/docstring.py
pythonbasictools/google_drive.py
pythonbasictools/hash_tools.py
pythonbasictools/lock.py
pythonbasictools/logging_tools.py
pythonbasictools/multiprocessing_tools.py
pythonbasictools/progress_bar.py
pythonbasictools/py.typed
pythonbasictools/run_output_file.py
pythonbasictools/slurm.py
pythonbasictools-0.0.3.dist-info/licenses/LICENSE
pythonbasictools-0.0.3.dist-info/METADATA
pythonbasictools-0.0.3.dist-info/WHEEL
pythonbasictools-0.0.3.dist-info/top_level.txt
pythonbasictools-0.0.3.dist-info/RECORD
