Metadata-Version: 2.4
Name: PythonBasicTools
Version: 0.0.3
Summary: Python Basic Tools
Author-email: Jérémie Gince <gincejeremie@gmail.com>
Project-URL: homepage, https://jeremiegince.github.io/PythonBasicTools/
Project-URL: Documentation, https://jeremiegince.github.io/PythonBasicTools/
Project-URL: Source, https://github.com/JeremieGince/PythonBasicTools
Classifier: License :: OSI Approved :: Apache Software License
Classifier: Programming Language :: Python :: 3
Classifier: Programming Language :: Python :: 3.9
Classifier: Programming Language :: Python :: 3.8
Classifier: Operating System :: OS Independent
Requires-Python: >=3.8
License-File: LICENSE
Requires-Dist: numpy<3.0.0,>=1.23
Requires-Dist: setuptools>=65.5.1
Requires-Dist: psutil>=5.9.6
Requires-Dist: importlib-metadata<9.0.0,>=8.7.0
Requires-Dist: tqdm>=4.62.3
Requires-Dist: pandas>=1.3.3
Dynamic: license-file
Dynamic: requires-python
